numexpr3/__config__.py
numexpr3/__init__.py
numexpr3/__version__.py
numexpr3/cpuinfo.py
numexpr3/interpreter.cp37-win_amd64.pyd
numexpr3/lookup.pkl
numexpr3/ne3compiler.py
numexpr3/utils.py
numexpr3/tests/__init__.py
numexpr3/tests/autotest_GENERATED.py
numexpr3/tests/autotest_stub.py
numexpr3/tests/problems.py
numexpr3/tests/simple_ne3.py
numexpr3/tests/test_numexpr.py
numexpr3-3.0.1a6.dist-info/AUTHORS.txt
numexpr3-3.0.1a6.dist-info/LICENSE.txt
numexpr3-3.0.1a6.dist-info/METADATA
numexpr3-3.0.1a6.dist-info/WHEEL
numexpr3-3.0.1a6.dist-info/top_level.txt
numexpr3-3.0.1a6.dist-info/RECORD
