Metadata-Version: 2.1
Name: numexpr3
Version: 3.0.1a6
Summary: Fast numerical expression evaluator for NumPy
Home-page: https://github.com/pydata/numexpr
Author: Robert A. McLeod, David M. Cooke, Francesc Alted, and others
Author-email: robbmcleod@gmail.com, faltet@gmail.com
License: BSD
Platform: UNKNOWN
Classifier: Development Status :: 3 - Alpha
Classifier: Intended Audience :: Developers
Classifier: Intended Audience :: Science/Research
Classifier: Intended Audience :: Information Technology
Classifier: License :: OSI Approved :: BSD License
Classifier: Programming Language :: Python
Classifier: Programming Language :: Python :: 3.6
Classifier: Programming Language :: Python :: 3.7
Classifier: Programming Language :: Python :: 3.8
Classifier: Topic :: Software Development :: Libraries :: Python Modules
Classifier: Operating System :: Microsoft :: Windows
Classifier: Operating System :: POSIX :: Linux
Requires-Dist: numpy (>=1.7)
Requires-Dist: setuptools (>=18.2)
